ColorizedOutput/__init__.py
ColorizedOutput/main.py
ColorizedOutput-0.0.2.dist-info/LICENSE
ColorizedOutput-0.0.2.dist-info/METADATA
ColorizedOutput-0.0.2.dist-info/WHEEL
ColorizedOutput-0.0.2.dist-info/top_level.txt
ColorizedOutput-0.0.2.dist-info/RECORD
