Metadata-Version: 2.1
Name: ColorizedOutput
Version: 0.0.2
Summary: Colorize(IPython style) the terminal output in VSCode.
Home-page: https://github.com/abc10605/ColorizedOutput
Author: abc10605
Author-email: chenghsuanho@gmail.com
License: UNKNOWN
Platform: UNKNOWN
Classifier: Programming Language :: Python :: 3
Classifier: License :: OSI Approved :: MIT License
Classifier: Operating System :: OS Independent
Requires-Python: >=3.6
License-File: LICENSE
